_your_package_version.py
pvtool/__init__.py
pvtool/customer_loader.py
pvtool/malo_id_validation.py
pvtool/network_loader.py
pvtool/py.typed
pvtool/resource_loader.py
pvtool/utils.py
pvtool/validation_manager.py
pvtool-0.3.3.dist-info/METADATA
pvtool-0.3.3.dist-info/WHEEL
pvtool-0.3.3.dist-info/licenses/LICENSE
pvtool-0.3.3.dist-info/RECORD
