Metadata-Version: 2.3
Name: pvtool
Version: 0.3.3
Summary: This tool contains validation logic for the BO4E migration data model (ibims). It uses the pvframework. 
Project-URL: Changelog, https://github.com/Hochfrequenz/pedantic-validator-tool/releases
Project-URL: Homepage, https://github.com/Hochfrequenz/pedantic-validator-tool
Author-email: Hochfrequenz Unternehmensberatung GmbH <info@hochfrequenz.de>
License: MIT
License-File: LICENSE
Keywords: bo4e,migration,python,validation
Classifier: Development Status :: 4 - Beta
Classifier: Environment :: Console
Classifier: Intended Audience :: Developers
Classifier: License :: OSI Approved :: MIT License
Classifier: Operating System :: OS Independent
Classifier: Programming Language :: Python
Classifier: Programming Language :: Python :: 3 :: Only
Classifier: Programming Language :: Python :: 3.11
Classifier: Programming Language :: Python :: 3.12
Requires-Python: >=3.11
Requires-Dist: bomf
Requires-Dist: ibims>=0.3.6
Requires-Dist: more-itertools
Requires-Dist: pvframework>=0.0.8
Requires-Dist: pydantic[email]
Requires-Dist: python-dateutil
Requires-Dist: pytz
Requires-Dist: schwifty
Provides-Extra: coverage
Requires-Dist: coverage==7.6.1; extra == 'coverage'
Provides-Extra: formatting
Requires-Dist: black==24.8.0; extra == 'formatting'
Requires-Dist: isort==5.13.2; extra == 'formatting'
Provides-Extra: linting
Requires-Dist: pylint==3.3.0; extra == 'linting'
Provides-Extra: packaging
Requires-Dist: build==1.2.2; extra == 'packaging'
Requires-Dist: twine==5.1.1; extra == 'packaging'
Provides-Extra: spellcheck
Requires-Dist: codespell==2.3.0; extra == 'spellcheck'
Provides-Extra: tests
Requires-Dist: pytest-asyncio==0.24.0; extra == 'tests'
Requires-Dist: pytest==8.3.3; extra == 'tests'
Provides-Extra: type-check
Requires-Dist: mypy==1.11.2; extra == 'type-check'
Requires-Dist: types-python-dateutil==2.9.0.20240906; extra == 'type-check'
Requires-Dist: types-pytz==2024.2.0.20240913; extra == 'type-check'
